Workbook
Name JR_PAGE_ANCHOR_0_1: 'PLANILHA ORCAMENTARIA'!$A$1
Name JR_PAGE_ANCHOR_1_1: 'RESUMO'!$A$1
Name JR_PAGE_ANCHOR_2_1: 'COMPOSICOES'!$A$1
Name JR_PAGE_ANCHOR_3_1: 'COMPOSICOES AUXILIARES'!$A$1
Name JR_PAGE_ANCHOR_4_1: 'ENCARGOS SOCIAIS'!$A$1
Name VALOR_TOTAL: 'PLANILHA ORCAMENTARIA'!$H$594
Name FATOR: RESUMO!$H$4
Name BDI: RESUMO!$H$5

Sheet PLANILHA ORCAMENTARIA
A3: ITEM | B3: CÓDIGO | C3: DESCRIÇÃO | D3: FONTE | E3: UND | F3: QUANTIDADE | G3: PREÇO UNITÁRIO R$ | H3: PREÇO TOTAL R$ | K3: PREÇO UNITÁRIO R$
A4: 1 | B4: ADMINISTRAÇÃO LOCAL DA OBRA | H4: =ROUND(SUM(H5:H5),2)
A5: 1.1 | B5: CXXXX | C5: ADMINISTRAÇÃO LOCAL DA OBRA - SEM DESONERAÇÃO, ENCARGOS SOCIAISINCORPORADOS NO PREÇO UNITÁRIO | E5: % | F5: 100 | G5: =COMPOSICOES!G18 | H5: =ROUND(ROUND(F5,2)*ROUND(G5,2),2) | K5: 16341.58 | L5: =G5-K5
A6: 2 | B6: SERVIÇOS INICIAIS | H6: =ROUND(H7+H29+H32+H36+H39,2)
A7: 2.1 | B7: INSTALAÇÃO DO CANTEIRO | H7: =ROUND(H8+H13+H20+H23+H26,2)
A8: 2.1.1 | B8: LIMPEZA DE ÁREA PARA CANTEIRO | H8: =ROUND(SUM(H9:H12),2)
A9: 2.1.1.1 | B9: 98525 | C9: LIMPEZA MECANIZADA DE CAMADA VEGETAL, VEGETAÇÃO E PEQUENAS ÁRVORES (DIÂMETRO DE TRONCO MENOR QUE 0,20 M), COM TRATOR DE ESTEIRAS.AF_03/2024 | D9: SINAPI | E9: M2 | F9: 566.74 | G9: =COMPOSICOES!G30 | H9: =ROUND(ROUND(F9,2)*ROUND(G9,2),2) | K9: 0.69 | L9: =G9-K9
A10: 2.1.1.2 | B10: 100980 | C10: CARGA, MANOBRA E DESCARGA DE SOLOS E MATERIAIS GRANULARES EM CAMINHÃO BASCULANTE 18 M³ - CARGA COM ESCAVADEIRA HIDRÁULICA (CAÇAMBA DE 1,20 M³ / 155 HP) E DESCARGA LIVRE(UNIDADE: M3). AF_07/2020 | D10: SINAPI | E10: M3 | F10: 73.68 | G10: =COMPOSICOES!G41 | H10: =ROUND(ROUND(F10,2)*ROUND(G10,2),2) | K10: 6.57 | L10: =G10-K10
A11: 2.1.1.3 | B11: 95877 | C11: TRANSPORTE COM CAMINHÃO BASCULANTE DE 18 M³, EM VIA URBANA PAVIMENTADA, DMT ATÉ 30 KM (UNIDADE:M3XKM). AF_07/2020 | D11: SINAPI | E11: M3XKM | F11: 368.38 | G11: =COMPOSICOES!G50 | H11: =ROUND(ROUND(F11,2)*ROUND(G11,2),2) | K11: 1.9 | L11: =G11-K11
A12: 2.1.1.4 | B12: C5185 | C12: DESTINAÇÃO FINAL DO RESÍDUO SOLIDO NÃO SEGREGADO EM TERRENOLICENCIADO - SEM TRANSPORTE | D12: SEINFRA | E12: M3 | F12: 73.68 | G12: =COMPOSICOES!G58 | H12: =ROUND(ROUND(F12,2)*ROUND(G12,2),2) | K12: 11.2 | L12: =G12-K12
A13: 2.1.2 | B13: ALOJAMENTO, VESTIÁRIO, ESCRITÓRIO E DEPÓSITO | H13: =ROUND(SUM(H14:H19),2)
A14: 2.1.2.1 | B14: 407PRÓPRIO | C14: BARRACÃO DE OBRA PARA LOJAMENTO/ESCRITÓRIO, PISO EM PINHO 3A, PAREDES EM COMPENSADO 10MM, COBERTURA EM TELHA FIBROCIMENTO 6MM, INCLUSOINSTALAÇÕES ELÉTRICAS E ESQUADRIAS | D14: Composiçõ es Próprias | E14: M² | F14: 25 | G14: =COMPOSICOES!G99 | H14: =ROUND(ROUND(F14,2)*ROUND(G14,2),2) | K14: 501.02 | L14: =G14-K14
A15: 2.1.2.2 | B15: 00010777 | C15: LOCACAO DE CONTAINER 2,30 X 4,30 M, ALT. 2,50 M, PARA SANITARIO, COM 3 BACIAS, 4 CHUVEIROS, 1 LAVATORIO E 1 MICTORIO (NÃO INCLUIMOBILIZACAO/DESMOBILIZACAO) | D15: SINAPI | E15: MES | F15: 8 | G15: =COMPOSICOES!G107 | H15: =ROUND(ROUND(F15,2)*ROUND(G15,2),2) | K15: 1674.73 | L15: =G15-K15
A16: 2.1.2.3 | B16: 00010775 | C16: LOCACAO DE CONTAINER 2,30 X 6,00 M, ALT. 2,50 M, COM 1 SANITARIO, PARA ESCRITORIO, COMPLETO, SEM DIVISORIAS INTERNAS (NAO INCLUIMOBILIZACAO/DESMOBILIZACAO) | D16: SINAPI | E16: MES | F16: 8 | G16: =COMPOSICOES!G115 | H16: =ROUND(ROUND(F16,2)*ROUND(G16,2),2) | K16: 1475 | L16: =G16-K16
A17: 2.1.2.4 | B17: 476 | C17: FRETE (CARGA, MANOBRA, DESCARGA E TRANSPORTE) DE CONTAINER EM CAMINHÃO CARROCERIA COM MUCK - TRAJETO MÁXIMO ATÉ 30KM | D17: Composiçõ | E17: UN | F17: 4 | G17: =COMPOSICOES!G127 | H17: =ROUND(ROUND(F17,2)*ROUND(G17,2),2) | K17: 286.87 | L17: =G17-K17
A18: 2.1.2.5 | B18: C0369 | C18: BARRACÃO ABERTO | D18: SEINFRA | E18: M2 | F18: 30 | G18: =COMPOSICOES!G153 | H18: =ROUND(ROUND(F18,2)*ROUND(G18,2),2) | K18: 151.62 | L18: =G18-K18
A19: 2.1.2.6 | B19: C2936 | C19: REFEITÓRIOS | D19: SEINFRA | E19: M2 | F19: 20 | G19: =COMPOSICOES!G185 | H19: =ROUND(ROUND(F19,2)*ROUND(G19,2),2) | K19: 372.84 | L19: =G19-K19
A20: 2.1.3 | B20: LIGAÇÕES PROVISÓRIAS | H20: =ROUND(SUM(H21:H22),2)
A21: 2.1.3.1 | B21: 369PRÓPRIO | C21: LIGAÇÃO PROVISÓRIA DE ÁGUA E ESGOTO PARA CANTEIRO DE OBRAS | D21: Composiçõ esPróprias | E21: UN | F21: 1 | G21: =COMPOSICOES!G240 | H21: =ROUND(ROUND(F21,2)*ROUND(G21,2),2) | K21: 4304.67 | L21: =G21-K21
A22: 2.1.3.2 | B22: 370PRÓPRIO | C22: LIGAÇÃO PROVISÓRIA LUZ E FORÇA | D22: Composiçõ esPróprias | E22: UN | F22: 1 | G22: =COMPOSICOES!G286 | H22: =ROUND(ROUND(F22,2)*ROUND(G22,2),2) | K22: 5321.9 | L22: =G22-K22
A23: 2.1.4 | B23: SINALIZAÇÃO E SEGURANÇA | H23: =ROUND(SUM(H24:H25),2)
A24: 2.1.4.1 | B24: 103689 | C24: FORNECIMENTO E INSTALAÇÃO DE PLACA DE OBRA COM CHAPA GALVANIZADA EESTRUTURA DE MADEIRA. AF_03/2022_PS | D24: SINAPI | E24: M2 | F24: 24.5 | G24: =COMPOSICOES!G304 | H24: =ROUND(ROUND(F24,2)*ROUND(G24,2),2) | K24: 467.74 | L24: =G24-K24
A25: 2.1.4.2 | B25: 98459 | C25: TAPUME COM TELHA METÁLICA.AF_03/2024 | D25: SINAPI | E25: M2 | F25: 190.68 | G25: =COMPOSICOES!G326 | H25: =ROUND(ROUND(F25,2)*ROUND(G25,2),2) | K25: 98.04 | L25: =G25-K25
A26: 2.1.5 | B26: EQUIPAMENTOS (LOCAÇÃO) | H26: =ROUND(SUM(H27:H28),2)
A27: 2.1.5.1 | B27: 371PRÓPRIO | C27: LOCAÇÃO DE ANDAIME METÁLICO TIPO FACHADEIRO (FORNECIMENTO,MONTAGEM E DESMONTAGEM) | D27: Composiçõ esPróprias | E27: M2XMÊ S | F27: 245.6 | G27: =COMPOSICOES!G338 | H27: =ROUND(ROUND(F27,2)*ROUND(G27,2),2) | K27: 25.97 | L27: =G27-K27
A28: 2.1.5.2 | B28: 97062 | C28: COLOCAÇÃO DE TELA EM ANDAIMEFACHADEIRO. AF_03/2024 | D28: SINAPI | E28: M2 | F28: 122.8 | G28: =COMPOSICOES!G351 | H28: =ROUND(ROUND(F28,2)*ROUND(G28,2),2) | K28: 5.83 | L28: =G28-K28
A29: 2.2 | B29: MOVIMENTO DE TERRA | H29: =ROUND(H30,2)
A30: 2.2.1 | B30: COMPACTAÇÃO DE ATERRO | H30: =ROUND(SUM(H31:H31),2)
A31: 2.2.1.1 | B31: 97083 | C31: COMPACTAÇÃO MECÂNICA DE SOLO PARA EXECUÇÃO DE RADIER, PISO DE CONCRETO OU LAJE SOBRE SOLO, COM COMPACTADOR DE SOLOS A PERCUSSÃO.AF_09/2021 | D31: SINAPI | E31: M2 | F31: 566.74 | G31: =COMPOSICOES!G364 | H31: =ROUND(ROUND(F31,2)*ROUND(G31,2),2) | K31: 3.65 | L31: =G31-K31
A32: 2.3 | B32: LOCAÇÃO DA OBRA | H32: =ROUND(H33,2)
A33: 2.3.1 | B33: EXECUÇÃO DE GABARITO | H33: =ROUND(SUM(H34:H35),2)
A34: 2.3.1.1 | B34: 99059 | C34: LOCAÇÃO CONVENCIONAL DE OBRA, UTILIZANDO GABARITO DE TÁBUAS CORRIDAS PONTALETADAS A CADA 2,00M -2 UTILIZAÇÕES. AF_03/2024 | D34: SINAPI | E34: M | F34: 101.88 | G34: =COMPOSICOES!G387 | H34: =ROUND(ROUND(F34,2)*ROUND(G34,2),2) | K34: 69.64 | L34: =G34-K34
A35: 2.3.1.2 | B35: C2873 | C35: LOCAÇÃO DA OBRA COM AUXÍLIOTOPOGRÁFICO (ÁREA ATÉ 5000 M2) | D35: SEINFRA | E35: M2 | F35: 566.74 | G35: =COMPOSICOES!G402 | H35: =ROUND(ROUND(F35,2)*ROUND(G35,2),2) | K35: 0.3 | L35: =G35-K35
A36: 2.4 | B36: LICENCIAMENTO AMBIENTAL | H36: =ROUND(SUM(H37:H38),2)
A37: 2.4.1 | B37: SOP1982 | C37: AUTORIZAÇÃO DE SUPRESSÃO DE VEGETAÇÃO (ASV) (IMPLANTAÇÃO DE ATIVIDADES E OBRAS DE UTILIDADE PÚBLICA E INTERESSE SOCIAL) - BDI =14,00 - BDI = 14,00 | D37: Composiçõ es Próprias | E37: UN | F37: 1 | G37: =COMPOSICOES!G410 | H37: =ROUND(ROUND(F37,2)*ROUND(G37,2),2) | K37: 1815.2 | L37: =G37-K37
A38: 2.4.2 | B38: SOP1988 | C38: TAXA PARA LICENCIAMENTO AMBIENTAL, CONFORME RESOLUÇÃO COEMA Nº02/2019 – ATIVIDADE 25.02 - BDI = 14,00 - BDI = 14,00 | D38: Composiçõ esPróprias | E38: UN | F38: 1 | G38: =COMPOSICOES!G418 | H38: =ROUND(ROUND(F38,2)*ROUND(G38,2),2) | K38: 5105.07 | L38: =G38-K38
A39: 2.5 | B39: MOBILIZAÇÃO DA OBRA | H39: =ROUND(SUM(H40:H40),2)
A40: 2.5.1 | B40: C4990 | C40: MOBILIZAÇÃO DE EQUIPAMENTOS EMCAMINHÃO EQUIPADO COM GUINDASTE | D40: SEINFRA | E40: KM | F40: 90.9 | G40: =COMPOSICOES!G426 | H40: =ROUND(ROUND(F40,2)*ROUND(G40,2),2) | K40: 3.2 | L40: =G40-K40
A41: 3 | B41: FUNDAÇÕES | H41: =ROUND(H42+H54+H63+H67+H71,2)
A42: 3.1 | B42: SERVIÇOS GERAIS EM FUNDAÇÕES | H42: =ROUND(H43+H46+H48+H51,2)
A43: 3.1.1 | B43: FUNDAÇÕES (ESCAVAÇÃO) | H43: =ROUND(SUM(H44:H45),2)
A44: 3.1.1.1 | B44: 96523 | C44: ESCAVAÇÃO MANUAL PARA BLOCO DE COROAMENTO OU SAPATA (INCLUINDO ESCAVAÇÃO PARA COLOCAÇÃO DE FÔRMAS). AF_01/2024 | D44: SINAPI | E44: M3 | F44: 348.1 | G44: =COMPOSICOES!G435 | H44: =ROUND(ROUND(F44,2)*ROUND(G44,2),2) | K44: 103.18 | L44: =G44-K44
A45: 3.1.1.2 | B45: 93358 | C45: ESCAVAÇÃO MANUAL DE VALA. AF_09/2024 | D45: SINAPI | E45: M3 | F45: 61.09 | G45: =COMPOSICOES!G443 | H45: =ROUND(ROUND(F45,2)*ROUND(G45,2),2) | K45: 93.19 | L45: =G45-K45
A46: 3.1.2 | B46: FUNDAÇÕES (REATERRO) | H46: =ROUND(SUM(H47:H47),2)
A47: 3.1.2.1 | B47: 93382 | C47: REATERRO MANUAL DE VALAS, COM COMPACTADOR DE SOLOS DEPERCUSSÃO. AF_08/2023 | D47: SINAPI | E47: M3 | F47: 290.04 | G47: =COMPOSICOES!G456 | H47: =ROUND(ROUND(F47,2)*ROUND(G47,2),2) | K47: 29.02 | L47: =G47-K47
A48: 3.1.3 | B48: FUNDAÇÕES (COMPACTAÇÃO) | H48: =ROUND(SUM(H49:H50),2)
A49: 3.1.3.1 | B49: 408 PRÓPRIO | C49: APILOAMENTO MANUAL DE FUNDO DE VALA COM MACO DE 30KG | D49: Composiçõ es | E49: M² | F49: 61.36 | G49: =COMPOSICOES!G464 | H49: =ROUND(ROUND(F49,2)*ROUND(G49,2),2) | K49: 35.34 | L49: =G49-K49
A50: 3.1.3.2 | B50: 409 PRÓPRIO | C50: APILOAMENTO MANUAL DE BLOCOS/SAPATAS COM MACO DE 30KG | D50: Composiçõ es | E50: M³ | F50: 18.41 | G50: =COMPOSICOES!G472 | H50: =ROUND(ROUND(F50,2)*ROUND(G50,2),2) | K50: 9.42 | L50: =G50-K50
A51: 3.1.4 | B51: FUNDAÇÕES (LASTRO) | H51: =ROUND(SUM(H52:H53),2)
A52: 3.1.4.1 | B52: C2860 | C52: LASTRO DE AREIA ADQUIRIDA | D52: SEINFRA | E52: M3 | F52: 18.41 | G52: =COMPOSICOES!G483 | H52: =ROUND(ROUND(F52,2)*ROUND(G52,2),2) | K52: 163.85 | L52: =G52-K52
A53: 3.1.4.2 | B53: 96619 | C53: LASTRO DE CONCRETO MAGRO, APLICADO EM BLOCOS DE COROAMENTO OU SAPATAS, ESPESSURA DE 5 CM. AF_01/2024 | D53: SINAPI | E53: M2 | F53: 61.36 | G53: =COMPOSICOES!G495 | H53: =ROUND(ROUND(F53,2)*ROUND(G53,2),2) | K53: 42.53 | L53: =G53-K53
A54: 3.2 | B54: ARMADURA PARA FUNDAÇÕES | H54: =ROUND(H55,2)
A55: 3.2.1 | B55: FUNDAÇÕES (ARMAÇÃO COM VERGALHÕES DE AÇO) | H55: =ROUND(SUM(H56:H62),2)
A56: 3.2.1.1 | B56: 104916 | C56: ARMAÇÃO DE SAPATA ISOLADA, VIGA BALDRAME E SAPATA CORRIDA UTILIZANDO AÇO CA-60 DE 5 MM - MONTAGEM. AF_01/2024 | D56: SINAPI | E56: KG | F56: 210.73 | G56: =COMPOSICOES!G511 | H56: =ROUND(ROUND(F56,2)*ROUND(G56,2),2) | K56: 16.68 | L56: =G56-K56
A57: 3.2.1.2 | B57: 104917 | C57: ARMAÇÃO DE SAPATA ISOLADA, VIGA BALDRAME E SAPATA CORRIDA UTILIZANDO AÇO CA-50 DE 6,3 MM - MONTAGEM. AF_01/2024 | D57: SINAPI | E57: KG | F57: 33.91 | G57: =COMPOSICOES!G527 | H57: =ROUND(ROUND(F57,2)*ROUND(G57,2),2) | K57: 15.14 | L57: =G57-K57
A58: 3.2.1.3 | B58: 104918 | C58: ARMAÇÃO DE SAPATA ISOLADA, VIGA BALDRAME E SAPATA CORRIDA UTILIZANDO AÇO CA-50 DE 8 MM - MONTAGEM. AF_01/2024 | D58: SINAPI | E58: KG | F58: 923.36 | G58: =COMPOSICOES!G543 | H58: =ROUND(ROUND(F58,2)*ROUND(G58,2),2) | K58: 13.82 | L58: =G58-K58
A59: 3.2.1.4 | B59: 104919 | C59: ARMAÇÃO DE SAPATA ISOLADA, VIGA BALDRAME E SAPATA CORRIDA UTILIZANDO AÇO CA-50 DE 10 MM - MONTAGEM. AF_01/2024 | D59: SINAPI | E59: KG | F59: 374.45 | G59: =COMPOSICOES!G559 | H59: =ROUND(ROUND(F59,2)*ROUND(G59,2),2) | K59: 12.19 | L59: =G59-K59
A60: 3.2.1.5 | B60: 104920 | C60: ARMAÇÃO DE BLOCO, SAPATA ISOLADA, VIGA BALDRAME E SAPATA CORRIDA UTILIZANDO AÇO CA-50 DE 12,5 MM - MONTAGEM. AF_01/2024 | D60: SINAPI | E60: KG | F60: 465.27 | G60: =COMPOSICOES!G575 | H60: =ROUND(ROUND(F60,2)*ROUND(G60,2),2) | K60: 10.26 | L60: =G60-K60
A61: 3.2.1.6 | B61: 104921 | C61: ARMAÇÃO DE BLOCO, SAPATA ISOLADA, VIGA BALDRAME E SAPATA CORRIDA UTILIZANDO AÇO CA-50 DE 16 MM - MONTAGEM. AF_01/2024 | D61: SINAPI | E61: KG | F61: 137.55 | G61: =COMPOSICOES!G591 | H61: =ROUND(ROUND(F61,2)*ROUND(G61,2),2) | K61: 9.58 | L61: =G61-K61
A62: 3.2.1.7 | B62: 104922 | C62: ARMAÇÃO DE BLOCO, SAPATA ISOLADA E SAPATA CORRIDA UTILIZANDO AÇO CA-50DE 20 MM - MONTAGEM. AF_01/2024 | D62: SINAPI | E62: KG | F62: 50.73 | G62: =COMPOSICOES!G607 | H62: =ROUND(ROUND(F62,2)*ROUND(G62,2),2) | K62: 10.43 | L62: =G62-K62
A63: 3.3 | B63: FÔRMA PARA FUNDAÇÕES | H63: =ROUND(H64,2)
A64: 3.3.1 | B64: FUNDAÇÕES (FÔRMA DE MADEIRA) | H64: =ROUND(SUM(H65:H66),2)
A65: 3.3.1.1 | B65: 96530 | C65: FABRICAÇÃO, MONTAGEM E DESMONTAGEM DE FÔRMA PARA VIGA BALDRAME, EM MADEIRA SERRADA, E=25 MM, 1 UTILIZAÇÃO. AF_01/2024 | D65: SINAPI | E65: M2 | F65: 218.32 | G65: =COMPOSICOES!G628 | H65: =ROUND(ROUND(F65,2)*ROUND(G65,2),2) | K65: 175.5 | L65: =G65-K65
A66: 3.3.1.2 | B66: 96529 | C66: FABRICAÇÃO, MONTAGEM E DESMONTAGEM DE FÔRMA PARA SAPATA, EM MADEIRA SERRADA, E=25 MM, 1 UTILIZAÇÃO. AF_01/2024 | D66: SINAPI | E66: M2 | F66: 36.72 | G66: =COMPOSICOES!G649 | H66: =ROUND(ROUND(F66,2)*ROUND(G66,2),2) | K66: 308.83 | L66: =G66-K66
A67: 3.4 | B67: CONCRETO PARA FUNDAÇÕES | H67: =ROUND(H68,2)
A68: 3.4.1 | B68: FUNDAÇÕES (CONCRETO ESTRUTURAL USINADO) | H68: =ROUND(SUM(H69:H70),2)
A69: 3.4.1.1 | B69: 96557 | C69: CONCRETAGEM DE BLOCO DE COROAMENTO OU VIGA BALDRAME, FCK 30 MPA, COM USO DE BOMBA - LANÇAMENTO, ADENSAMENTO E ACABAMENTO.AF_01/2024 | D69: SINAPI | E69: M3 | F69: 14.71 | G69: =COMPOSICOES!G665 | H69: =ROUND(ROUND(F69,2)*ROUND(G69,2),2) | K69: 700.03 | L69: =G69-K69
A70: 3.4.1.2 | B70: 96558 | C70: CONCRETAGEM DE SAPATA, FCK 30 MPA, COM USO DE BOMBA - LANÇAMENTO, ADENSAMENTO E ACABAMENTO. AF_01/2024 | D70: SINAPI | E70: M3 | F70: 19.18 | G70: =COMPOSICOES!G681 | H70: =ROUND(ROUND(F70,2)*ROUND(G70,2),2) | K70: 733.38 | L70: =G70-K70
A71: 3.5 | B71: IMPERMEABILIZAÇÃO EM FUNDAÇÕES | H71: =ROUND(H72,2)
A72: 3.5.1 | B72: FUNDAÇÕES (IMPERMEABILIZAÇÃO COM TINTA ASFÁLTICA) | H72: =ROUND(SUM(H73:H73),2)
A73: 3.5.1.1 | B73: 98557 | C73: IMPERMEABILIZAÇÃO DE SUPERFÍCIE COM EMULSÃO ASFÁLTICA, 2 DEMÃOS.AF_09/2023 | D73: SINAPI | E73: M2 | F73: 218.32 | G73: =COMPOSICOES!G693 | H73: =ROUND(ROUND(F73,2)*ROUND(G73,2),2) | K73: 42.09 | L73: =G73-K73
A74: 4 | B74: SUPERESTRUTURA | H74: =ROUND(H75+H99,2)
A75: 4.1 | B75: PILARES, VIGAS E LAJES DE CONCRETO ARMADO | H75: =ROUND(H76+H83+H90+H96,2)
A76: 4.1.1 | B76: SUPERESTRUTURA (ARMADURA PILARES E VIGAS - VERGALHÕES DE AÇO) | H76: =ROUND(SUM(H77:H82),2)
A77: 4.1.1.1 | B77: 92759 | C77: ARMAÇÃO DE PILAR OU VIGA DE ESTRUTURA CONVENCIONAL DE CONCRETO ARMADO UTILIZANDO AÇO CA-60 DE 5,0 MM - MONTAGEM. AF_06/2022 | D77: SINAPI | E77: KG | F77: 911 | G77: =COMPOSICOES!G709 | H77: =ROUND(ROUND(F77,2)*ROUND(G77,2),2) | K77: 13.81 | L77: =G77-K77
A78: 4.1.1.2 | B78: 92760 | C78: ARMAÇÃO DE PILAR OU VIGA DE ESTRUTURA CONVENCIONAL DE CONCRETO ARMADO UTILIZANDO AÇO CA-50 DE 6,3 MM - MONTAGEM. AF_06/2022 | D78: SINAPI | E78: KG | F78: 566.6 | G78: =COMPOSICOES!G725 | H78: =ROUND(ROUND(F78,2)*ROUND(G78,2),2) | K78: 12.71 | L78: =G78-K78
A79: 4.1.1.3 | B79: 92761 | C79: ARMAÇÃO DE PILAR OU VIGA DE ESTRUTURA CONVENCIONAL DE CONCRETO ARMADO UTILIZANDO AÇO CA-50 DE 8,0 MM - MONTAGEM. AF_06/2022 | D79: SINAPI | E79: KG | F79: 257.4 | G79: =COMPOSICOES!G741 | H79: =ROUND(ROUND(F79,2)*ROUND(G79,2),2) | K79: 11.73 | L79: =G79-K79
A80: 4.1.1.4 | B80: 92762 | C80: ARMAÇÃO DE PILAR OU VIGA DE ESTRUTURA CONVENCIONAL DE CONCRETO ARMADO UTILIZANDO AÇO CA-50 DE 10,0 MM - MONTAGEM.AF_06/2022 | D80: SINAPI | E80: KG | F80: 2550 | G80: =COMPOSICOES!G757 | H80: =ROUND(ROUND(F80,2)*ROUND(G80,2),2) | K80: 10.34 | L80: =G80-K80
A81: 4.1.1.5 | B81: 92763 | C81: ARMAÇÃO DE PILAR OU VIGA DE ESTRUTURA CONVENCIONAL DE CONCRETO ARMADO UTILIZANDO AÇO CA-50 DE 12,5 MM - MONTAGEM.AF_06/2022 | D81: SINAPI | E81: KG | F81: 1550.3 | G81: =COMPOSICOES!G773 | H81: =ROUND(ROUND(F81,2)*ROUND(G81,2),2) | K81: 8.61 | L81: =G81-K81
A82: 4.1.1.6 | B82: 92764 | C82: ARMAÇÃO DE PILAR OU VIGA DE ESTRUTURA CONVENCIONAL DE CONCRETO ARMADO UTILIZANDO AÇO CA-50 DE 16,0 MM - MONTAGEM.AF_06/2022 | D82: SINAPI | E82: KG | F82: 1282.6 | G82: =COMPOSICOES!G789 | H82: =ROUND(ROUND(F82,2)*ROUND(G82,2),2) | K82: 8.27 | L82: =G82-K82
A83: 4.1.2 | B83: SUPERESTRUTURA (ARMADURA LAJES) | H83: =ROUND(SUM(H84:H89),2)
A84: 4.1.2.1 | B84: 92768 | C84: ARMAÇÃO DE LAJE DE ESTRUTURA CONVENCIONAL DE CONCRETO ARMADO UTILIZANDO AÇO CA-60 DE 5,0 MM - MONTAGEM. AF_06/2022 | D84: SINAPI | E84: KG | F84: 924.8 | G84: =COMPOSICOES!G805 | H84: =ROUND(ROUND(F84,2)*ROUND(G84,2),2) | K84: 13.2 | L84: =G84-K84
A85: 4.1.2.2 | B85: 92769 | C85: ARMAÇÃO DE LAJE DE ESTRUTURA CONVENCIONAL DE CONCRETO ARMADO UTILIZANDO AÇO CA-50 DE 6,3 MM - MONTAGEM. AF_06/2022 | D85: SINAPI | E85: KG | F85: 387.5 | G85: =COMPOSICOES!G821 | H85: =ROUND(ROUND(F85,2)*ROUND(G85,2),2) | K85: 12.13 | L85: =G85-K85
A86: 4.1.2.3 | B86: 92770 | C86: ARMAÇÃO DE LAJE DE ESTRUTURA CONVENCIONAL DE CONCRETO ARMADO UTILIZANDO AÇO CA-50 DE 8,0 MM - MONTAGEM. AF_06/2022 | D86: SINAPI | E86: KG | F86: 1638.2 | G86: =COMPOSICOES!G837 | H86: =ROUND(ROUND(F86,2)*ROUND(G86,2),2) | K86: 11.19 | L86: =G86-K86
A87: 4.1.2.4 | B87: 92771 | C87: ARMAÇÃO DE LAJE DE ESTRUTURA CONVENCIONAL DE CONCRETO ARMADOUTILIZANDO AÇO CA-50 DE 10,0 MM - MONTAGEM. AF_06/2022 | D87: SINAPI | E87: KG | F87: 1946.2 | G87: =COMPOSICOES!G853 | H87: =ROUND(ROUND(F87,2)*ROUND(G87,2),2) | K87: 9.84 | L87: =G87-K87
A88: 4.1.2.5 | B88: 92772 | C88: ARMAÇÃO DE LAJE DE ESTRUTURA CONVENCIONAL DE CONCRETO ARMADO UTILIZANDO AÇO CA-50 DE 12,5 MM - MONTAGEM. AF_06/2022 | D88: SINAPI | E88: KG | F88: 825.4 | G88: =COMPOSICOES!G869 | H88: =ROUND(ROUND(F88,2)*ROUND(G88,2),2) | K88: 8.16 | L88: =G88-K88
A89: 4.1.2.6 | B89: 92773 | C89: ARMAÇÃO DE LAJE DE ESTRUTURA CONVENCIONAL DE CONCRETO ARMADO UTILIZANDO AÇO CA-50 DE 16,0 MM - MONTAGEM. AF_06/2022 | D89: SINAPI | E89: KG | F89: 803.5 | G89: =COMPOSICOES!G884 | H89: =ROUND(ROUND(F89,2)*ROUND(G89,2),2) | K89: 7.97 | L89: =G89-K89
A90: 4.1.3 | B90: SUPERESTRUTURA (FÔRMAS) | H90: =ROUND(SUM(H91:H95),2)
A91: 4.1.3.1 | B91: 92268 | C91: FABRICAÇÃO DE FÔRMA PARA LAJES, EM CHAPA DE MADEIRA COMPENSADAPLASTIFICADA, E = 18 MM. AF_09/2020 | D91: SINAPI | E91: M2 | F91: 345.69 | G91: =COMPOSICOES!G900 | H91: =ROUND(ROUND(F91,2)*ROUND(G91,2),2) | K91: 103.84 | L91: =G91-K91
A92: 4.1.3.2 | B92: 92263 | C92: FABRICAÇÃO DE FÔRMA PARA PILARES E ESTRUTURAS SIMILARES, EM CHAPA DE MADEIRA COMPENSADA RESINADA, E = 17 MM. AF_09/2020 | D92: SINAPI | E92: M2 | F92: 181.84 | G92: =COMPOSICOES!G919 | H92: =ROUND(ROUND(F92,2)*ROUND(G92,2),2) | K92: 194.45 | L92: =G92-K92
A93: 4.1.3.3 | B93: 92266 | C93: FABRICAÇÃO DE FÔRMA PARA VIGAS, EM CHAPA DE MADEIRA COMPENSADAPLASTIFICADA, E = 18 MM. AF_09/2020 | D93: SINAPI | E93: M2 | F93: 311.98 | G93: =COMPOSICOES!G938 | H93: =ROUND(ROUND(F93,2)*ROUND(G93,2),2) | K93: 185.71 | L93: =G93-K93
A94: 4.1.3.4 | B94: 101792 | C94: ESCORAMENTO DE FÔRMAS DE LAJE EM MADEIRA NÃO APARELHADA, PÉ-DIREITO SIMPLES, INCLUSO TRAVAMENTO, 4 UTILIZAÇÕES. AF_09/2020 | D94: SINAPI | E94: M3 | F94: 42.3 | G94: =COMPOSICOES!G954 | H94: =ROUND(ROUND(F94,2)*ROUND(G94,2),2) | K94: 19.7 | L94: =G94-K94
A95: 4.1.3.5 | B95: 101793 | C95: ESCORAMENTO DE FÔRMAS DE LAJE EM MADEIRA NÃO APARELHADA, PÉ-DIREITO DUPLO, INCLUSO TRAVAMENTO, 4 UTILIZAÇÕES. AF_09/2020 | D95: SINAPI | E95: M3 | F95: 11.2 | G95: =COMPOSICOES!G970 | H95: =ROUND(ROUND(F95,2)*ROUND(G95,2),2) | K95: 31.17 | L95: =G95-K95
A96: 4.1.4 | B96: SUPERESTRUTURA (CONCRETO USINADO) | H96: =ROUND(SUM(H97:H98),2)
A97: 4.1.4.1 | B97: 394 PRÓPRIO | C97: CONCRETAGEM DE PILARES, FCK= 30MPA, COM USO DE BOMBA - LANÇAMENTO, ADENSAMENTO E ACABAMENTO. AF_02/2022_PS | D97: Composiçõ es Próprias | E97: M³ | F97: 11.31 | G97: =COMPOSICOES!G987 | H97: =ROUND(ROUND(F97,2)*ROUND(G97,2),2) | K97: 653.36 | L97: =G97-K97
A98: 4.1.4.2 | B98: 395 PRÓPRIO | C98: CONCRETAGEM DE VIGAS E LAJES, FCK= 30MPA, PARA LAJES MACIÇAS OU NERVURADAS COM USO DE BOMBA - LANÇAMENTO, ADENSAMENTO EACABAMENTO. AF_02/2022_PS | D98: Composiçõ es Próprias | E98: M³ | F98: 82.62 | G98: =COMPOSICOES!G1004 | H98: =ROUND(ROUND(F98,2)*ROUND(G98,2),2) | K98: 654.36 | L98: =G98-K98
A99: 4.2 | B99: CONTROLE TECNOLÓGICO DE CONCRETO | H99: =ROUND(SUM(H100:H100),2)
A100: 4.2.1 | B100: SOP2059 | C100: CONTROLE TECNOLÓGICO DE CONCRETO "COM" MOLDAGEM DE CORPOS DE PROVA, MENSALIDADE DE LABORATORISTA DE ATÉ 44 HS, COLETA CORPOS DE PROVA E EMISSÃO CERTIFICADOS, DE 61 A 100 KM, DE SEGUNDA A SEXTA | D100: Composiçõ es Próprias | E100: MÊS | F100: 2 | G100: =COMPOSICOES!G1012 | H100: =ROUND(ROUND(F100,2)*ROUND(G100,2),2) | K100: 12540 | L100: =G100-K100
A101: 5 | B101: COBERTURA | H101: =ROUND(H102+H106+H111+H119+H122,2)
A102: 5.1 | B102: SERVIÇOS GERAIS EM COBERTURA | H102: =ROUND(H103,2)
...

Sheet RESUMO
A4: 1 | B4: ADMINISTRAÇÃO LOCAL DA OBRA | D4: ='PLANILHA ORCAMENTARIA'!H4 | E4: =(D4/$D$23)*100 | G4: FATOR | H4: 1
A5: 2 | B5: SERVIÇOS INICIAIS | D5: ='PLANILHA ORCAMENTARIA'!H6 | E5: =(D5/$D$23)*100 | G5: BDI | H5: 22,98%
A6: 3 | B6: FUNDAÇÕES | D6: ='PLANILHA ORCAMENTARIA'!H41 | E6: =(D6/$D$23)*100
A7: 4 | B7: SUPERESTRUTURA | D7: ='PLANILHA ORCAMENTARIA'!H74 | E7: =(D7/$D$23)*100
A8: 5 | B8: COBERTURA | D8: ='PLANILHA ORCAMENTARIA'!H101 | E8: =(D8/$D$23)*100
A9: 6 | B9: PAREDES E PAINÉIS | D9: ='PLANILHA ORCAMENTARIA'!H125 | E9: =(D9/$D$23)*100
A10: 7 | B10: ESQUADRIAS | D10: ='PLANILHA ORCAMENTARIA'!H146 | E10: =(D10/$D$23)*100
A11: 8 | B11: SISTEMAS HIDRÁULICOS, SANITÁRIOS E DE COMBATE A INCÊNDIO (HSI) | D11: ='PLANILHA ORCAMENTARIA'!H158 | E11: =(D11/$D$23)*100
A12: 9 | B12: SISTEMA ELÉTRICO (ELE) + SISTEMA DE VOZ E DADOS (NET) | D12: ='PLANILHA ORCAMENTARIA'!H277 | E12: =(D12/$D$23)*100
A13: 10 | B13: SISTEMAS DE AR CONDICIONADO, VENTILAÇÃO E EXAUSTÃO (ACD) | D13: ='PLANILHA ORCAMENTARIA'!H391 | E13: =(D13/$D$23)*100
A14: 11 | B14: REVESTIMENTOS PRIMÁRIOS | D14: ='PLANILHA ORCAMENTARIA'!H426 | E14: =(D14/$D$23)*100
A15: 12 | B15: ACABAMENTOS (REVESTIMENTO PARA TETO, PAREDE E PISO) | D15: ='PLANILHA ORCAMENTARIA'!H437 | E15: =(D15/$D$23)*100
A16: 13 | B16: ACABAMENTOS (HIDROSSANITÁRIOS) | D16: ='PLANILHA ORCAMENTARIA'!H455 | E16: =(D16/$D$23)*100
A17: 14 | B17: ACABAMENTOS (ELÉTRICOS, VOZ, DADOS E TV) | D17: ='PLANILHA ORCAMENTARIA'!H506 | E17: =(D17/$D$23)*100
A18: 15 | B18: PINTURA | D18: ='PLANILHA ORCAMENTARIA'!H538 | E18: =(D18/$D$23)*100
A19: 16 | B19: URBANIZAÇÃO | D19: ='PLANILHA ORCAMENTARIA'!H549 | E19: =(D19/$D$23)*100
A20: 17 | B20: DESMOBILIZAÇÃO DE CANTEIRO | D20: ='PLANILHA ORCAMENTARIA'!H558 | E20: =(D20/$D$23)*100
A21: 18 | B21: SERVIÇOS NÃO FINANCIADOS PELO CONTRATO DE REPASSE | D21: ='PLANILHA ORCAMENTARIA'!H591 | E21: =(D21/$D$23)*100
A22: 19 | B22: Benefícios e Despesas Indiretas (BDI) | D22: ='PLANILHA ORCAMENTARIA'!H592 | E22: 0
C23: VALOR BDI TOTAL: | D23: ='PLANILHA ORCAMENTARIA'!H593 | E23: 100
C24: VALOR ORÇAMENTO: | D24: 3225595.3
C25: VALOR TOTAL: | D25: 3969434.3

Sheet COMPOSICOES
A3: 1.1. ​CXXXX​ ADMINISTRAÇÃO LOCAL DA OBRA - SEM DESONERAÇÃO, ENCARGOS SOCIAISINCORPORADOS NO PREÇO UNITÁRIO​ (%)
A4: COTAÇÃO / ADMINISTRAÇÃO LOCAL DE OBRA (C/ ENCARGOS) | C4: FONTE | D4: UNID | E4: COEFICIENTE | F4: PREÇO UNITÁRIO | G4: TOTAL
A5: I8610 | B5: COMPUTADOR | C5: SEINFRA | D5: UNxMÊS | E5: 1 | F5: 170 | G5: =ROUND(ROUND(E5,8)*F5,2) | L5: 1 | M5: 170 | N5: =(M5-F5)
E6: TOTAL COTAÇÃO / ADMINISTRAÇÃO LOCAL DE OBRA (C/ ENCARGOS): | G6: =SUM(G5:G5)
A7: Mão de Obra | C7: FONTE | D7: UNID | E7: COEFICIENTE | F7: PREÇO UNITÁRIO | G7: TOTAL
A8: I8601 | B8: CADISTA | C8: SEINFRA | D8: MÊS | E8: =L8*FATOR | F8: 5851.46 | G8: =ROUND(ROUND(E8,8)*F8,2) | L8: 0.1 | M8: 5851.46 | N8: =(M8-F8)
A9: I8617 | B9: VIGIA | C9: SEINFRA | D9: MÊS | E9: =L9*FATOR | F9: 3687.34 | G9: =ROUND(ROUND(E9,8)*F9,2) | L9: 1 | M9: 3687.34 | N9: =(M9-F9)
E10: TOTAL Mão de Obra: | G10: =SUM(G8:G9)
A11: Mão de Obra com Encargos Complementares | C11: FONTE | D11: UNID | E11: COEFICIENTE | F11: PREÇO UNITÁRIO | G11: TOTAL
A12: 93563 | B12: ALMOXARIFE COM ENCARGOS COMPLEMENTARES | C12: SINAPI | D12: MES | E12: =L12*FATOR | F12: ='COMPOSICOES AUXILIARES'!G123 | G12: =ROUND(ROUND(E12,8)*F12,2) | L12: 1 | M12: 4298.73 | N12: =(M12-F12)
A13: 93572 | B13: ENCARREGADO GERAL DE OBRAS COM ENCARGOS COMPLEMENTARES | C13: SINAPI | D13: MES | E13: =L13*FATOR | F13: ='COMPOSICOES AUXILIARES'!G1905 | G13: =ROUND(ROUND(E13,8)*F13,2) | L13: 1 | M13: 5117.87 | N13: =(M13-F13)
A14: 93567 | B14: ENGENHEIRO CIVIL DE OBRA PLENO COM ENCARGOS COMPLEMENTARES | C14: SINAPI | D14: MES | E14: =L14*FATOR | F14: ='COMPOSICOES AUXILIARES'!G1948 | G14: =ROUND(ROUND(E14,8)*F14,2) | L14: 0.1 | M14: 24824.87 | N14: =(M14-F14)
E15: TOTAL Mão de Obra com Encargos Complementares: | G15: =SUM(G12:G14)
E16: VALOR: | G16: =SUM(G10,G15)
E17: VALOR BDI (23.08%): | G17: =ROUNDDOWN(G16*BDI,2)
E18: VALOR COM BDI: | G18: =G17 + G16
A20: 2.1.1.1. ​98525​ LIMPEZA MECANIZADA DE CAMADA VEGETAL, VEGETAÇÃO E PEQUENAS ÁRVORES (DIÂMETRO DE TRONCO MENOR QUE 0,20 M), COM TRATOR DE ESTEIRAS.AF_03/2024​ (M2)
A21: Equipamento Custo Horário | C21: FONTE | D21: UNID | E21: COEFICIENTE | F21: PREÇO UNITÁRIO | G21: TOTAL
A22: 89031 | B22: TRATOR DE ESTEIRAS, POTÊNCIA 100 HP, PESO OPERACIONAL 9,4 T, COM LÂMINA 2,19 M3 - CHI DIURNO. AF_06/2014 | C22: SINAPI | D22: CHI | E22: 0.0029 | F22: ='COMPOSICOES AUXILIARES'!G3615 | G22: =TRUNC(TRUNC(E22,8)*F22,2) | L22: 0.0029 | M22: 83.96 | N22: =(M22-F22)
A23: 89032 | B23: TRATOR DE ESTEIRAS, POTÊNCIA 100 HP, PESO OPERACIONAL 9,4 T, COM LÂMINA 2,19 M3 - CHP DIURNO. AF_06/2014 | C23: SINAPI | D23: CHP | E23: 0.0017 | F23: ='COMPOSICOES AUXILIARES'!G3629 | G23: =TRUNC(TRUNC(E23,8)*F23,2) | L23: 0.0017 | M23: 206.64 | N23: =(M23-F23)
E24: TOTAL Equipamento Custo Horário: | G24: =SUM(G22:G23)
A25: Mão de Obra com Encargos Complementares | C25: FONTE | D25: UNID | E25: COEFICIENTE | F25: PREÇO UNITÁRIO | G25: TOTAL
A26: 88441 | B26: JARDINEIRO COM ENCARGOS COMPLEMENTARES | C26: SINAPI | D26: H | E26: =L26*FATOR | F26: ='COMPOSICOES AUXILIARES'!G2344 | G26: =TRUNC(TRUNC(E26,8)*F26,2) | L26: 0.0046 | M26: 23.91 | N26: =(M26-F26)
E27: TOTAL Mão de Obra com Encargos Complementares: | G27: =SUM(G26:G26)
E28: VALOR: | G28: =SUM(G24,G27)
E29: VALOR BDI (23.08%): | G29: =ROUNDDOWN(G28*BDI,2)
E30: VALOR COM BDI: | G30: =G29 + G28
A32: 2.1.1.2. ​100980​ CARGA, MANOBRA E DESCARGA DE SOLOS E MATERIAIS GRANULARES EM CAMINHÃO BASCULANTE 18 M³ - CARGA COM ESCAVADEIRA HIDRÁULICA (CAÇAMBA DE 1,20 M³ / 155 HP) E DESCARGA LIVRE(UNIDADE: M3). AF_07/2020​ (M3)
A33: Equipamento Custo Horário | C33: FONTE | D33: UNID | E33: COEFICIENTE | F33: PREÇO UNITÁRIO | G33: TOTAL
A34: 89884 | B34: CAMINHÃO BASCULANTE 18 M3, COM CAVALO MECÂNICO DE CAPACIDADE MÁXIMA DE TRAÇÃO COMBINADO DE 45000 KG, POTÊNCIA 330 CV, INCLUSIVE SEMIREBOQUE COM CAÇAMBA METÁLICA - CHI DIURNO. AF_12/2014 | C34: SINAPI | D34: CHI | E34: 0.0077 | F34: ='COMPOSICOES AUXILIARES'!G738 | G34: =TRUNC(TRUNC(E34,8)*F34,2) | L34: 0.0077 | M34: 98.1 | N34: =(M34-F34)
A35: 89883 | B35: CAMINHÃO BASCULANTE 18 M3, COM CAVALO MECÂNICO DE CAPACIDADE MÁXIMA DE TRAÇÃO COMBINADO DE 45000 KG, POTÊNCIA 330 CV, INCLUSIVE SEMIREBOQUE COM CAÇAMBA METÁLICA - CHP DIURNO. AF_12/2014 | C35: SINAPI | D35: CHP | E35: 0.0111 | F35: ='COMPOSICOES AUXILIARES'!G753 | G35: =TRUNC(TRUNC(E35,8)*F35,2) | L35: 0.0111 | M35: 373.41 | N35: =(M35-F35)
A36: 88908 | B36: ESCAVADEIRA HIDRÁULICA SOBRE ESTEIRAS, CAÇAMBA 1,20 M3, PESO OPERACIONAL 21 T, POTÊNCIA BRUTA 155 HP - CHI DIURNO. AF_06/2014 | C36: SINAPI | D36: CHI | E36: 0.0056 | F36: ='COMPOSICOES AUXILIARES'!G1978 | G36: =TRUNC(TRUNC(E36,8)*F36,2) | L36: 0.0056 | M36: 104.69 | N36: =(M36-F36)
A37: 88907 | B37: ESCAVADEIRA HIDRÁULICA SOBRE ESTEIRAS, CAÇAMBA 1,20 M3, PESO OPERACIONAL 21 T, POTÊNCIA BRUTA 155 HP - CHP DIURNO. AF_06/2014 | C37: SINAPI | D37: CHP | E37: 0.0042 | F37: ='COMPOSICOES AUXILIARES'!G1992 | G37: =TRUNC(TRUNC(E37,8)*F37,2) | L37: 0.0042 | M37: 262.65 | N37: =(M37-F37)
E38: TOTAL Equipamento Custo Horário: | G38: =SUM(G34:G37)
E39: VALOR: | G39: =SUM(G38)
E40: VALOR BDI (23.08%): | G40: =ROUNDDOWN(G39*BDI,2)
E41: VALOR COM BDI: | G41: =G40 + G39
A43: 2.1.1.3. ​95877​ TRANSPORTE COM CAMINHÃO BASCULANTE DE 18 M³, EM VIA URBANA PAVIMENTADA, DMT ATÉ 30 KM (UNIDADE:M3XKM). AF_07/2020​ (M3XKM)
A44: Equipamento Custo Horário | C44: FONTE | D44: UNID | E44: COEFICIENTE | F44: PREÇO UNITÁRIO | G44: TOTAL
A45: 89884 | B45: CAMINHÃO BASCULANTE 18 M3, COM CAVALO MECÂNICO DE CAPACIDADE MÁXIMA DE TRAÇÃO COMBINADO DE 45000 KG, POTÊNCIA 330 CV, INCLUSIVE SEMIREBOQUE COM CAÇAMBA METÁLICA - CHI DIURNO. AF_12/2014 | C45: SINAPI | D45: CHI | E45: 0.002 | F45: ='COMPOSICOES AUXILIARES'!G738 | G45: =TRUNC(TRUNC(E45,8)*F45,2) | L45: 0.002 | M45: 98.1 | N45: =(M45-F45)
A46: 89883 | B46: CAMINHÃO BASCULANTE 18 M3, COM CAVALO MECÂNICO DE CAPACIDADE MÁXIMA DE TRAÇÃO COMBINADO DE 45000 KG, POTÊNCIA 330 CV, INCLUSIVE SEMIREBOQUE COM CAÇAMBA METÁLICA - CHP DIURNO. AF_12/2014 | C46: SINAPI | D46: CHP | E46: 0.0046 | F46: ='COMPOSICOES AUXILIARES'!G753 | G46: =TRUNC(TRUNC(E46,8)*F46,2) | L46: 0.0046 | M46: 373.41 | N46: =(M46-F46)
E47: TOTAL Equipamento Custo Horário: | G47: =SUM(G45:G46)
E48: VALOR: | G48: =SUM(G47)
E49: VALOR BDI (23.08%): | G49: =ROUNDDOWN(G48*BDI,2)
E50: VALOR COM BDI: | G50: =G49 + G48
A52: 2.1.1.4. ​C5185​ DESTINAÇÃO FINAL DO RESÍDUO SOLIDO NÃO SEGREGADO EM TERRENOLICENCIADO - SEM TRANSPORTE​ (M3)
A53: Material | C53: FONTE | D53: UNID | E53: COEFICIENTE | F53: PREÇO UNITÁRIO | G53: TOTAL
A54: I10260 | B54: RECEBIMENTO DE MATERIAL SEGREGADO | C54: SEINFRA | D54: M3 | E54: 1 | F54: =ROUND(M54*FATOR, 2) | G54: =ROUND(ROUND(E54,8)*F54,4) | L54: 1 | M54: 11.2 | N54: =(M54-F54)
E55: TOTAL Material: | G55: =SUM(G54:G54)
E56: VALOR: | G56: =SUM(G55)
E57: VALOR BDI (23.08%): | G57: =ROUNDDOWN(G56*BDI,2)
E58: VALOR COM BDI: | G58: =G57 + G56
A60: 2.1.2.1. ​407PRÓPRIO​ BARRACÃO DE OBRA PARA LOJAMENTO/ESCRITÓRIO, PISO EM PINHO 3A, PAREDES EM COMPENSADO 10MM, COBERTURA EM TELHA FIBROCIMENTO 6MM, INCLUSOINSTALAÇÕES ELÉTRICAS E ESQUADRIAS​ (M²)
A61: Material | C61: FONTE | D61: UNID | E61: COEFICIENTE | F61: PREÇO UNITÁRIO | G61: TOTAL
A62: 00005085 | B62: CADEADO SIMPLES, CORPO EM LATAO MACICO, COM LARGURA DE 35 MM E ALTURA DE APROX 30 MM, HASTE CEMENTADA (NAO LONGA), EM ACO TEMPERADO COM DIAMETRO DE APROX 6,0 MM, INCLUINDO 2 CHAVES | C62: SINAPI | D62: UN | E62: 0.0058 | F62: =ROUND(M62*FATOR, 2) | G62: =ROUND(ROUND(E62,8)*F62,2) | L62: 0.0058 | M62: 31.26 | N62: =(M62-F62)
A63: 00004777 | B63: CANTONEIRA ACO ABAS IGUAIS (QUALQUER BITOLA), ESPESSURA ENTRE 1/8" E 1/4" | C63: SINAPI | D63: KG | E63: 0.303 | F63: =ROUND(M63*FATOR, 2) | G63: =ROUND(ROUND(E63,8)*F63,2) | L63: 0.303 | M63: 8.02 | N63: =(M63-F63)
A64: 00001346 | B64: CHAPA/PAINEL DE MADEIRA COMPENSADA PLASTIFICADA (MADEIRITE PLASTIFICADO) PARA FORMA DE CONCRETO, DE 2200 X 1100 MM, E = 10 MM | C64: SINAPI | D64: M2 | E64: 0.386 | F64: =ROUND(M64*FATOR, 2) | G64: =ROUND(ROUND(E64,8)*F64,2) | L64: 0.386 | M64: 56.85 | N64: =(M64-F64)
A65: 00001607 | B65: CONJUNTO ARRUELAS DE VEDACAO 5/16" PARA TELHA FIBROCIMENTO (UMA ARRUELA METALICA E UMA ARRUELA PVC - CONICAS) | C65: SINAPI | D65: CJ | E65: 0.214 | F65: =ROUND(M65*FATOR, 2) | G65: =ROUND(ROUND(E65,8)*F65,2) | L65: 0.214 | M65: 0.21 | N65: =(M65-F65)
A66: 00011891 | B66: CORDAO DE COBRE, FLEXIVEL, TORCIDO, CLASSE 4 OU 5, ISOLACAO EM PVC/D, 300 V, 2 CONDUTORES DE 2,5 MM2 | C66: SINAPI | D66: M | E66: 0.536 | F66: =ROUND(M66*FATOR, 2) | G66: =ROUND(ROUND(E66,8)*F66,2) | L66: 0.536 | M66: 5.89 | N66: =(M66-F66)
A67: 00002370 | B67: DISJUNTOR TIPO NEMA, MONOPOLAR 10 ATE 30A, TENSAO MAXIMA DE 240 V | C67: SINAPI | D67: UN | E67: 0.0057 | F67: =ROUND(M67*FATOR, 2) | G67: =ROUND(ROUND(E67,8)*F67,2) | L67: 0.0057 | M67: 12 | N67: =(M67-F67)
A68: 00002432 | B68: DOBRADICA EM ACO/FERRO, 3 1/2" X 3", E= 1,9 A 2 MM, COM ANEL, CROMADO OU ZINCADO, TAMPA BOLA, COM PARAFUSOS | C68: SINAPI | D68: UN | E68: 0.0346 | F68: =ROUND(M68*FATOR, 2) | G68: =ROUND(ROUND(E68,8)*F68,2) | L68: 0.0346 | M68: 29.64 | N68: =(M68-F68)
A69: 00011467 | B69: FECHADURA DE SOBREPOR TIPO CAIXAO, EM FERRO COM ACABAMENTO RESINADO, SEM MACANETA, SEM CILINDRO, INCLUINDO CHAVE TIPO SIMPLES | C69: SINAPI | D69: UN | E69: 0.0058 | F69: =ROUND(M69*FATOR, 2) | G69: =ROUND(ROUND(E69,8)*F69,2) | L69: 0.0058 | M69: 19.7 | N69: =(M69-F69)
A70: 00021127 | B70: FITA ISOLANTE ADESIVA ANTICHAMA, USO ATE 750 V, EM ROLO DE 19 MM X 5 M | C70: SINAPI | D70: UN | E70: 0.024 | F70: =ROUND(M70*FATOR, 2) | G70: =ROUND(ROUND(E70,8)*F70,2) | L70: 0.024 | M70: 3.78 | N70: =(M70-F70)
A71: 00012128 | B71: INTERRUPTOR SIMPLES 10A, 250V, CONJUNTO MONTADO PARA SOBREPOR 4" X 2" (CAIXA + MODULO) | C71: SINAPI | D71: UN | E71: 0.023 | F71: =ROUND(M71*FATOR, 2) | G71: =ROUND(ROUND(E71,8)*F71,2) | L71: 0.023 | M71: 9.34 | N71: =(M71-F71)
A72: 00039389 | B72: LUMINARIA LED REFLETOR RETANGULAR BIVOLT, LUZ BRANCA, 10 W | C72: SINAPI | D72: UN | E72: 0.0461 | F72: =ROUND(M72*FATOR, 2) | G72: =ROUND(ROUND(E72,8)*F72,2) | L72: 0.0461 | M72: 10.72 | N72: =(M72-F72)
A73: 00011056 | B73: PARAFUSO ROSCA SOBERBA ZINCADO CABECA CHATA FENDA SIMPLES 3,8 X 30 MM (1.1/4") | C73: SINAPI | D73: UN | E73: 1.28 | F73: =ROUND(M73*FATOR, 2) | G73: =ROUND(ROUND(E73,8)*F73,2) | L73: 1.28 | M73: 0.07 | N73: =(M73-F73)
... A83: 00004448 | B83: VIGA *7,5 X 15 CM EM PINUS, MISTA OU EQUIVALENTE DA REGIAO - BRUTA | C83: SINAPI | D83: M | E83: 0.7 | F83: =ROUND(M83*FATOR, 2) | G83: =ROUND(ROUND(E83,8)*F83,2) | L83: 0.7 | M83: 29.27 | N83: =(M83-F83)
E84: TOTAL Material: | G84: =SUM(G62:G83)
A85: Mão de Obra com Encargos Complementares | C85: FONTE | D85: UNID | E85: COEFICIENTE | F85: PREÇO UNITÁRIO | G85: TOTAL
A86: 88251 | B86: AUXILIAR DE SERRALHEIRO COM ENCARGOS COMPLEMENTARES | C86: SINAPI | D86: H | E86: =L86*FATOR | F86: ='COMPOSICOES AUXILIARES'!G543 | G86: =ROUND(ROUND(E86,8)*F86,2) | L86: 0.07 | M86: 24.77 | N86: =(M86-F86)
A87: 88261 | B87: CARPINTEIRO DE ESQUADRIAS COM ENCARGOS COMPLEMENTARES | C87: SINAPI | D87: H | E87: =L87*FATOR | F87: ='COMPOSICOES AUXILIARES'!G924 | G87: =ROUND(ROUND(E87,8)*F87,2) | L87: 6.34 | M87: 29.16 | N87: =(M87-F87)
A88: 88264 | B88: ELETRICISTA COM ENCARGOS COMPLEMENTARES | C88: SINAPI | D88: H | E88: =L88*FATOR | F88: ='COMPOSICOES AUXILIARES'!G505 | G88: =ROUND(ROUND(E88,8)*F88,2) | L88: 0.3 | M88: 30.96 | N88: =(M88-F88)
A89: 88315 | B89: SERRALHEIRO COM ENCARGOS COMPLEMENTARES | C89: SINAPI | D89: H | E89: =L89*FATOR | F89: ='COMPOSICOES AUXILIARES'!G543 | G89: =ROUND(ROUND(E89,8)*F89,2) | L89: 0.07 | M89: 30.37 | N89: =(M89-F89)
A90: 88316 | B90: SERVENTE COM ENCARGOS COMPLEMENTARES | C90: SINAPI | D90: H | E90: =L90*FATOR | F90: ='COMPOSICOES AUXILIARES'!G3390 | G90: =ROUND(ROUND(E90,8)*F90,2) | L90: 7.03 | M90: 23.56 | N90: =(M90-F90)
E91: TOTAL Mão de Obra com Encargos Complementares: | G91: =SUM(G86:G90)
A92: Serviço | C92: FONTE | D92: UNID | E92: COEFICIENTE | F92: PREÇO UNITÁRIO | G92: TOTAL
A93: 94969 | B93: CONCRETO FCK = 15MPA, TRAÇO 1:3,4:3,5 (EM MASSA SECA DE CIMENTO/ AREIA MÉDIA/ BRITA 1) - PREPARO MECÂNICO COM BETONEIRA 600 L. AF_05/2021 | C93: SINAPI | D93: M3 | E93: 0.015 | F93: ='COMPOSICOES AUXILIARES'!G1160 | G93: =ROUND(ROUND(E93,8)*F93,2) | L93: 0.015 | M93: 462.58 | N93: =(M93-F93)
A94: 103670 | B94: LANÇAMENTO COM USO DE BALDES, ADENSAMENTO E ACABAMENTO DE CONCRETO EM ESTRUTURAS. AF_02/2022 | C94: SINAPI | D94: M3 | E94: 0.015 | F94: ='COMPOSICOES AUXILIARES'!G2374 | G94: =ROUND(ROUND(E94,8)*F94,2) | L94: 0.015 | M94: 325.41 | N94: =(M94-F94)
A95: 98679 | B95: PISO CIMENTADO, TRAÇO 1:3 (CIMENTO E AREIA), ACABAMENTO LISO, ESPESSURA 2,0 CM, PREPARO MECÂNICO DA ARGAMASSA. AF_09/2020 | C95: SINAPI | D95: M2 | E95: 1 | F95: ='COMPOSICOES AUXILIARES'!G3099 | G95: =ROUND(ROUND(E95,8)*F95,2) | L95: 1 | M95: 40.05 | N95: =(M95-F95)
E96: TOTAL Serviço: | G96: =SUM(G93:G95)
E97: VALOR: | G97: =SUM(G96,G91,G84)
E98: VALOR BDI (23.08%): | G98: =ROUNDDOWN(G97*BDI,2)
E99: VALOR COM BDI: | G99: =G98 + G97
A101: 2.1.2.2. ​00010777​ LOCACAO DE CONTAINER 2,30 X 4,30 M, ALT. 2,50 M, PARA SANITARIO, COM 3 BACIAS, 4 CHUVEIROS, 1 LAVATORIO E 1 MICTORIO (NÃO INCLUIMOBILIZACAO/DESMOBILIZACAO)​ (MES)
A102: Equipamento | C102: FONTE | D102: UNID | E102: COEFICIENTE | F102: PREÇO UNITÁRIO | G102: TOTAL
A103: 00010777 | B103: LOCACAO DE CONTAINER 2,30 X 4,30 M, ALT. 2,50 M, PARA SANITARIO, COM 3 BACIAS, 4 CHUVEIROS, 1 LAVATORIO E 1 MICTORIO (NAO INCLUI MOBILIZACAO/DESMOBILIZACAO) | C103: SINAPI | D103: MES | E103: 1 | F103: =ROUND(M103*FATOR, 2) | G103: =TRUNC(TRUNC(E103,8)*F103,2) | L103: 1 | M103: 1674.73 | N103: =(M103-F103)
E104: TOTAL Equipamento: | G104: =SUM(G103:G103)
E105: VALOR: | G105: =SUM(G104)
E106: VALOR BDI (23.08%): | G106: =ROUNDDOWN(G105*BDI,2)
E107: VALOR COM BDI: | G107: =G106 + G105
A109: 2.1.2.3. ​00010775​ LOCACAO DE CONTAINER 2,30 X 6,00 M, ALT. 2,50 M, COM 1 SANITARIO, PARA ESCRITORIO, COMPLETO, SEM DIVISORIAS INTERNAS (NAO INCLUIMOBILIZACAO/DESMOBILIZACAO)​ (MES)
A110: Equipamento | C110: FONTE | D110: UNID | E110: COEFICIENTE | F110: PREÇO UNITÁRIO | G110: TOTAL
A111: 00010775 | B111: LOCACAO DE CONTAINER 2,30 X 6,00 M, ALT. 2,50 M, COM 1 SANITARIO, PARA ESCRITORIO, COMPLETO, SEM DIVISORIAS INTERNAS (NAO INCLUI MOBILIZACAO/DESMOBILIZACAO) | C111: SINAPI | D111: MES | E111: 1 | F111: =ROUND(M111*FATOR, 2) | G111: =TRUNC(TRUNC(E111,8)*F111,2) | L111: 1 | M111: 1475 | N111: =(M111-F111)
E112: TOTAL Equipamento: | G112: =SUM(G111:G111)
E113: VALOR: | G113: =SUM(G112)
E114: VALOR BDI (23.08%): | G114: =ROUNDDOWN(G113*BDI,2)
E115: VALOR COM BDI: | G115: =G114 + G113
A117: 2.1.2.4. ​476​ FRETE (CARGA, MANOBRA, DESCARGA E TRANSPORTE) DE CONTAINER EM CAMINHÃO CARROCERIA COM MUCK - TRAJETO MÁXIMO ATÉ 30KM​ (UN)
A118: Equipamento Custo Horário | C118: FONTE | D118: UNID | E118: COEFICIENTE | F118: PREÇO UNITÁRIO | G118: TOTAL
A119: 5930 | B119: GUINDAUTO HIDRÁULICO, CAPACIDADE MÁXIMA DE CARGA 6200 KG, MOMENTO MÁXIMO DE CARGA 11,7 TM, ALCANCE MÁXIMO HORIZONTAL 9,70 M, INCLUSIVE CAMINHÃO TOCO PBT 16.000 KG, POTÊNCIA DE 189 CV - CHI DIURNO. AF_06/2014 | C119: SINAPI | D119: CHI | E119: 0.0931 | F119: ='COMPOSICOES AUXILIARES'!G2199 | G119: =ROUND(ROUND(E119,8)*F119,2) | L119: 0.0931 | M119: 79.83 | N119: =(M119-F119)
...

Sheet COMPOSICOES AUXILIARES
A3: ​C0034​ ADIÇÃO DE IMPERMEABILIZANTE PARA CONCRETO ESTRUTURAL​ (M3)
A4: Material | C4: FONTE | D4: UNID | E4: COEFICIENTE | F4: PREÇO UNITÁRIO | G4: TOTAL
A5: I2421 | B5: SIKA 1 | C5: SEINFRA | D5: KG | E5: 7.92 | F5: =ROUND(M5*FATOR, 2) | G5: =ROUND(ROUND(E5,8)*F5,4) | L5: 7.92 | M5: 7 | N5: =(M5-F5)
E6: TOTAL Material: | G6: =SUM(G5:G5)
E7: VALOR: | G7: =SUM(G6)
E8: VALOR BDI (23.08%): | G8: =ROUNDDOWN(G7*BDI,2)
E9: VALOR COM BDI: | G9: =G8 + G7
A11: ​88238​ AJUDANTE DE ARMADOR COM ENCARGOS COMPLEMENTARES​ (H)
A12: Encargos Complementares | C12: FONTE | D12: UNID | E12: COEFICIENTE | F12: PREÇO UNITÁRIO | G12: TOTAL
A13: 00037370 | B13: ALIMENTACAO - HORISTA (COLETADO CAIXA - ENCARGOS COMPLEMENTARES) | C13: SINAPI | D13: H | E13: 1 | F13: 3.62 | G13: =TRUNC(TRUNC(E13,8)*F13,2) | L13: 1 | M13: 3.62 | N13: =(M13-F13)
A14: 00043489 | B14: EPI - FAMILIA PEDREIRO - HORISTA (ENCARGOS COMPLEMENTARES - COLETADO CAIXA) | C14: SINAPI | D14: H | E14: 1 | F14: 1.31 | G14: =TRUNC(TRUNC(E14,8)*F14,2) | L14: 1 | M14: 1.31 | N14: =(M14-F14)
A15: 00037372 | B15: EXAMES - HORISTA (COLETADO CAIXA - ENCARGOS COMPLEMENTARES) | C15: SINAPI | D15: H | E15: 1 | F15: 1.43 | G15: =TRUNC(TRUNC(E15,8)*F15,2) | L15: 1 | M15: 1.43 | N15: =(M15-F15)
A16: 00043465 | B16: FERRAMENTAS - FAMILIA PEDREIRO - HORISTA (ENCARGOS COMPLEMENTARES - COLETADO CAIXA) | C16: SINAPI | D16: H | E16: 1 | F16: 0.78 | G16: =TRUNC(TRUNC(E16,8)*F16,2) | L16: 1 | M16: 0.78 | N16: =(M16-F16)
A17: 00037373 | B17: SEGURO - HORISTA (COLETADO CAIXA - ENCARGOS COMPLEMENTARES) | C17: SINAPI | D17: H | E17: 1 | F17: 0.08 | G17: =TRUNC(TRUNC(E17,8)*F17,2) | L17: 1 | M17: 0.08 | N17: =(M17-F17)
A18: 00037371 | B18: TRANSPORTE - HORISTA (COLETADO CAIXA - ENCARGOS COMPLEMENTARES) | C18: SINAPI | D18: H | E18: 1 | F18: 1.09 | G18: =TRUNC(TRUNC(E18,8)*F18,2) | L18: 1 | M18: 1.09 | N18: =(M18-F18)
E19: TOTAL Encargos Complementares: | G19: =SUM(G13:G18)
A20: Mão de Obra | C20: FONTE | D20: UNID | E20: COEFICIENTE | F20: PREÇO UNITÁRIO | G20: TOTAL
A21: 00006114 | B21: AJUDANTE DE ARMADOR (HORISTA) | C21: SINAPI | D21: H | E21: =L21*FATOR | F21: 16.28 | G21: =TRUNC(TRUNC(E21,8)*F21,2) | L21: 1 | M21: 16.28 | N21: =(M21-F21)
E22: TOTAL Mão de Obra: | G22: =SUM(G21:G21)
A23: Serviço | C23: FONTE | D23: UNID | E23: COEFICIENTE | F23: PREÇO UNITÁRIO | G23: TOTAL
A24: 95308 | B24: CURSO DE CAPACITAÇÃO PARA AJUDANTE DE ARMADOR (ENCARGOS COMPLEMENTARES) - HORISTA | C24: SINAPI | D24: H | E24: 1 | F24: =G1483 | G24: =TRUNC(TRUNC(E24,8)*F24,2) | L24: 1 | M24: 0.18 | N24: =(M24-F24)
E25: TOTAL Serviço: | G25: =SUM(G24:G24)
E26: VALOR: | G26: =SUM(G25,G19,G22)
E27: VALOR BDI (23.08%): | G27: =ROUNDDOWN(G26*BDI,2)
E28: VALOR COM BDI: | G28: =G27 + G26
A30: ​ED-50363​ AJUDANTE DE BOMBEIRO/ENCANADOR COM ENCARGOS COMPLEMENTARES​ (hora)
A31: MÃO DE OBRA | D31: UNID | E31: CONSUMO | F31: SALÁRIO HORA | G31: CUSTO HORÁRIO
A32: MOED-20131 | B32: AJUDANTE DE BOMBEIRO/ ENCANADOR (MODALIDADE: HORISTA| ENCARGOS | D32: h | E32: =L32*FATOR | F32: 18.232 | G32: =ROUND(ROUND(E32,7)*F32,4) | L32: 1 | M32: 18.232 | N32: =(M32-F32)
E33: TOTAL MÃO DE OBRA: | G33: =SUM(G32:G32)
E34: Custo Horário da Execução: | G34: =G33
E35: Produção da Equipe: | G35: 1
E36: Custo Unitário da Execução: | G36: =ROUND(G34/G35, 4)
A37: MATERIAIS | D37: UNID | E37: CONSUMO | F37: =G700 | G37: CUSTO UNITÁRIO
A38: MATED-13096 | B38: CESTA BÁSICA/ALIMENTAÇÃO - HORISTA ( ENCARGOS COMPLEMENTARES) | D38: hora | E38: 1 | F38: 2.12 | G38: =ROUND(ROUND(E38,7)*F38,4) | L38: 1 | M38: 2.12 | N38: =(M38-F38)
A39: MATED-13099 | B39: EXAMES - HORISTA (ENCARGOS COMPLEMENTARES) | D39: hora | E39: 1 | F39: 1.43 | G39: =ROUND(ROUND(E39,7)*F39,4) | L39: 1 | M39: 1.43 | N39: =(M39-F39)
A40: MATED-13098 | B40: SEGURO - HORISTA (ENCARGOS COMPLEMENTARES) | D40: hora | E40: 1 | F40: 0.08 | G40: =ROUND(ROUND(E40,7)*F40,4) | L40: 1 | M40: 0.08 | N40: =(M40-F40)
A41: MATED-13097 | B41: TRANSPORTE - HORISTA (ENCARGOS COMPLEMENTARES) | D41: hora | E41: 1 | F41: 0.86 | G41: =ROUND(ROUND(E41,7)*F41,4) | L41: 1 | M41: 0.86 | N41: =(M41-F41)
E42: TOTAL MATERIAIS: | G42: =SUM(G38:G41)
A43: SERVIÇOS | D43: UNID | E43: CONSUMO | F43: PREÇO UNITÁRIO | G43: CUSTO UNITÁRIO
A44: ED-5227 | B44: CURSO DE CAPACITAÇÃO PARA AUXILIAR DE ENCANADOR OU BOMBEIRO HIDRÁULICO ( ENCARGOS COMPLEMENTARES) - HORISTA | D44: hora | E44: 1 | F44: 0.33 | G44: =ROUND(ROUND(E44,7)*F44,4) | L44: 1 | M44: 0.33 | N44: =(M44-F44)
A45: ED-14645 | B45: EPI PARA AJUDANTE DE BOMBEIRO/ENCANADOR - HORISTA (ENCARGOS COMPLEMENTARES) | D45: hora | E45: 1 | F45: =G1957 | G45: =ROUND(ROUND(E45,7)*F45,4) | L45: 1 | M45: 1.13 | N45: =(M45-F45)
A46: ED-14681 | B46: FERRAMENTAS PARA AJUDANTE DE BOMBEIRO/ ENCANADOR - HORISTA (ENCARGOS COMPLEMENTARES) | D46: hora | E46: 1 | F46: =G2130 | G46: =ROUND(ROUND(E46,7)*F46,4) | L46: 1 | M46: 0.31 | N46: =(M46-F46)
E47: TOTAL SERVIÇOS: | G47: =SUM(G44:G46)
E48: Custo Direto Total: | G48: =SUM(G36,G42,G47)
E49: VALOR: | G49: =SUM(G33,G42,G47)
E50: VALOR BDI (23.08%): | G50: =ROUNDDOWN(G49*BDI,2)
E51: VALOR COM BDI: | G51: =G50 + G49
A53: ​88239​ AJUDANTE DE CARPINTEIRO COM ENCARGOS COMPLEMENTARES​ (H)
A54: Encargos Complementares | C54: FONTE | D54: UNID | E54: COEFICIENTE | F54: PREÇO UNITÁRIO | G54: TOTAL
A55: 00037370 | B55: ALIMENTACAO - HORISTA (COLETADO CAIXA - ENCARGOS COMPLEMENTARES) | C55: SINAPI | D55: H | E55: 1 | F55: 3.62 | G55: =TRUNC(TRUNC(E55,8)*F55,2) | L55: 1 | M55: 3.62 | N55: =(M55-F55)
A56: 00043483 | B56: EPI - FAMILIA CARPINTEIRO DE FORMAS - HORISTA (ENCARGOS COMPLEMENTARES - COLETADO CAIXA) | C56: SINAPI | D56: H | E56: 1 | F56: 1.43 | G56: =TRUNC(TRUNC(E56,8)*F56,2) | L56: 1 | M56: 1.43 | N56: =(M56-F56)
A57: 00037372 | B57: EXAMES - HORISTA (COLETADO CAIXA - ENCARGOS COMPLEMENTARES) | C57: SINAPI | D57: H | E57: 1 | F57: 1.43 | G57: =TRUNC(TRUNC(E57,8)*F57,2) | L57: 1 | M57: 1.43 | N57: =(M57-F57)
A58: 00043459 | B58: FERRAMENTAS - FAMILIA CARPINTEIRO DE FORMAS - HORISTA (ENCARGOS COMPLEMENTARES - COLETADO CAIXA) | C58: SINAPI | D58: H | E58: 1 | F58: 0.44 | G58: =TRUNC(TRUNC(E58,8)*F58,2) | L58: 1 | M58: 0.44 | N58: =(M58-F58)
A59: 00037373 | B59: SEGURO - HORISTA (COLETADO CAIXA - ENCARGOS COMPLEMENTARES) | C59: SINAPI | D59: H | E59: 1 | F59: 0.08 | G59: =TRUNC(TRUNC(E59,8)*F59,2) | L59: 1 | M59: 0.08 | N59: =(M59-F59)
A60: 00037371 | B60: TRANSPORTE - HORISTA (COLETADO CAIXA - ENCARGOS COMPLEMENTARES) | C60: SINAPI | D60: H | E60: 1 | F60: 1.09 | G60: =TRUNC(TRUNC(E60,8)*F60,2) | L60: 1 | M60: 1.09 | N60: =(M60-F60)
E61: TOTAL Encargos Complementares: | G61: =SUM(G55:G60)
A62: Mão de Obra | C62: FONTE | D62: UNID | E62: COEFICIENTE | F62: PREÇO UNITÁRIO | G62: TOTAL
A63: 00006117 | B63: CARPINTEIRO AUXILIAR (HORISTA) | C63: SINAPI | D63: H | E63: =L63*FATOR | F63: 16.28 | G63: =TRUNC(TRUNC(E63,8)*F63,2) | L63: 1 | M63: 16.28 | N63: =(M63-F63)
E64: TOTAL Mão de Obra: | G64: =SUM(G63:G63)
A65: Serviço | C65: FONTE | D65: UNID | E65: COEFICIENTE | F65: PREÇO UNITÁRIO | G65: TOTAL
A66: 95309 | B66: CURSO DE CAPACITAÇÃO PARA AJUDANTE DE CARPINTEIRO (ENCARGOS COMPLEMENTARES) - HORISTA | C66: SINAPI | D66: H | E66: 1 | F66: =G1491 | G66: =TRUNC(TRUNC(E66,8)*F66,2) | L66: 1 | M66: 0.24 | N66: =(M66-F66)
E67: TOTAL Serviço: | G67: =SUM(G66:G66)
E68: VALOR: | G68: =SUM(G64,G67,G61)
E69: VALOR BDI (23.08%): | G69: =ROUNDDOWN(G68*BDI,2)
E70: VALOR COM BDI: | G70: =G69 + G68
A72: ​88240​ AJUDANTE DE ESTRUTURA METÁLICA COM ENCARGOS COMPLEMENTARES​ (H)
A73: Encargos Complementares | C73: FONTE | D73: UNID | E73: COEFICIENTE | F73: PREÇO UNITÁRIO | G73: TOTAL
A74: 00037370 | B74: ALIMENTACAO - HORISTA (COLETADO CAIXA - ENCARGOS COMPLEMENTARES) | C74: SINAPI | D74: H | E74: 1 | F74: 3.62 | G74: =TRUNC(TRUNC(E74,8)*F74,2) | L74: 1 | M74: 3.62 | N74: =(M74-F74)
A75: 00043488 | B75: EPI - FAMILIA OPERADOR ESCAVADEIRA - HORISTA (ENCARGOS COMPLEMENTARES - COLETADO CAIXA) | C75: SINAPI | D75: H | E75: 1 | F75: 0.89 | G75: =TRUNC(TRUNC(E75,8)*F75,2) | L75: 1 | M75: 0.89 | N75: =(M75-F75)
A76: 00037372 | B76: EXAMES - HORISTA (COLETADO CAIXA - ENCARGOS COMPLEMENTARES) | C76: SINAPI | D76: H | E76: 1 | F76: 1.43 | G76: =TRUNC(TRUNC(E76,8)*F76,2) | L76: 1 | M76: 1.43 | N76: =(M76-F76)
A77: 00043464 | B77: FERRAMENTAS - FAMILIA OPERADOR ESCAVADEIRA - HORISTA (ENCARGOS COMPLEMENTARES - COLETADO CAIXA) | C77: SINAPI | D77: H | E77: 1 | F77: 0.01 | G77: =TRUNC(TRUNC(E77,8)*F77,2) | L77: 1 | M77: 0.01 | N77: =(M77-F77)
A78: 00037373 | B78: SEGURO - HORISTA (COLETADO CAIXA - ENCARGOS COMPLEMENTARES) | C78: SINAPI | D78: H | E78: 1 | F78: 0.08 | G78: =TRUNC(TRUNC(E78,8)*F78,2) | L78: 1 | M78: 0.08 | N78: =(M78-F78)
A79: 00037371 | B79: TRANSPORTE - HORISTA (COLETADO CAIXA - ENCARGOS COMPLEMENTARES) | C79: SINAPI | D79: H | E79: 1 | F79: 1.09 | G79: =TRUNC(TRUNC(E79,8)*F79,2) | L79: 1 | M79: 1.09 | N79: =(M79-F79)
E80: TOTAL Encargos Complementares: | G80: =SUM(G74:G79)
A81: Mão de Obra | C81: FONTE | D81: UNID | E81: COEFICIENTE | F81: PREÇO UNITÁRIO | G81: TOTAL
A82: 00044499 | B82: AJUDANTE DE ESTRUTURAS METALICAS (HORISTA) | C82: SINAPI | D82: H | E82: =L82*FATOR | F82: 16.28 | G82: =TRUNC(TRUNC(E82,8)*F82,2) | L82: 1 | M82: 16.28 | N82: =(M82-F82)
E83: TOTAL Mão de Obra: | G83: =SUM(G82:G82)
A84: Serviço | C84: FONTE | D84: UNID | E84: COEFICIENTE | F84: PREÇO UNITÁRIO | G84: TOTAL
A85: 95310 | B85: CURSO DE CAPACITAÇÃO PARA AJUDANTE DE ESTRUTURA METÁLICA (ENCARGOS COMPLEMENTARES) - HORISTA | C85: SINAPI | D85: H | E85: 1 | F85: =G1499 | G85: =TRUNC(TRUNC(E85,8)*F85,2) | L85: 1 | M85: 0.18 | N85: =(M85-F85)
E86: TOTAL Serviço: | G86: =SUM(G85:G85)
E87: VALOR: | G87: =SUM(G80,G83,G86)
E88: VALOR BDI (23.08%): | G88: =ROUNDDOWN(G87*BDI,2)
E89: VALOR COM BDI: | G89: =G88 + G87
A91: ​88243​ AJUDANTE ESPECIALIZADO COM ENCARGOS COMPLEMENTARES​ (H)
A92: Encargos Complementares | C92: FONTE | D92: UNID | E92: COEFICIENTE | F92: PREÇO UNITÁRIO | G92: TOTAL
A93: 00037370 | B93: ALIMENTACAO - HORISTA (COLETADO CAIXA - ENCARGOS COMPLEMENTARES) | C93: SINAPI | D93: H | E93: 1 | F93: 3.62 | G93: =TRUNC(TRUNC(E93,8)*F93,2) | L93: 1 | M93: 3.62 | N93: =(M93-F93)
A94: 00043491 | B94: EPI - FAMILIA SERVENTE - HORISTA (ENCARGOS COMPLEMENTARES - COLETADO CAIXA) | C94: SINAPI | D94: H | E94: 1 | F94: 1.39 | G94: =TRUNC(TRUNC(E94,8)*F94,2) | L94: 1 | M94: 1.39 | N94: =(M94-F94)
A95: 00037372 | B95: EXAMES - HORISTA (COLETADO CAIXA - ENCARGOS COMPLEMENTARES) | C95: SINAPI | D95: H | E95: 1 | F95: 1.43 | G95: =TRUNC(TRUNC(E95,8)*F95,2) | L95: 1 | M95: 1.43 | N95: =(M95-F95)
A96: 00043467 | B96: FERRAMENTAS - FAMILIA SERVENTE - HORISTA (ENCARGOS COMPLEMENTARES - COLETADO CAIXA) | C96: SINAPI | D96: H | E96: 1 | F96: 0.61 | G96: =TRUNC(TRUNC(E96,8)*F96,2) | L96: 1 | M96: 0.61 | N96: =(M96-F96)
A97: 00037373 | B97: SEGURO - HORISTA (COLETADO CAIXA - ENCARGOS COMPLEMENTARES) | C97: SINAPI | D97: H | E97: 1 | F97: 0.08 | G97: =TRUNC(TRUNC(E97,8)*F97,2) | L97: 1 | M97: 0.08 | N97: =(M97-F97)
A98: 00037371 | B98: TRANSPORTE - HORISTA (COLETADO CAIXA - ENCARGOS COMPLEMENTARES) | C98: SINAPI | D98: H | E98: 1 | F98: 1.09 | G98: =TRUNC(TRUNC(E98,8)*F98,2) | L98: 1 | M98: 1.09 | N98: =(M98-F98)
E99: TOTAL Encargos Complementares: | G99: =SUM(G93:G98)
A100: Mão de Obra | C100: FONTE | D100: UNID | E100: COEFICIENTE | F100: PREÇO UNITÁRIO | G100: TOTAL
A101: 00000242 | B101: AJUDANTE ESPECIALIZADO (HORISTA) | C101: SINAPI | D101: H | E101: =L101*FATOR | F101: 15.37 | G101: =TRUNC(TRUNC(E101,8)*F101,2) | L101: 1 | M101: 15.37 | N101: =(M101-F101)
E102: TOTAL Mão de Obra: | G102: =SUM(G101:G101)
A103: Serviço | C103: FONTE | D103: UNID | E103: COEFICIENTE | F103: PREÇO UNITÁRIO | G103: TOTAL
A104: 95313 | B104: CURSO DE CAPACITAÇÃO PARA AJUDANTE ESPECIALIZADO (ENCARGOS COMPLEMENTARES) - HORISTA | C104: SINAPI | D104: H | E104: 1 | F104: =G1507 | G104: =TRUNC(TRUNC(E104,8)*F104,2) | L104: 1 | M104: 0.17 | N104: =(M104-F104)
E105: TOTAL Serviço: | G105: =SUM(G104:G104)
E106: VALOR: | G106: =SUM(G105,G99,G102)
E107: VALOR BDI (23.08%): | G107: =ROUNDDOWN(G106*BDI,2)
...

Sheet ENCARGOS SOCIAIS
A3: COD | B3: DESCRIÇÃO | C3: HORISTA % | E3: MENSALISTA %
A5: A | B5: GRUPO A
A6: A1 | B6: INSS | C6: 20 | E6: 20
A7: A2 | B7: SESI | C7: 1.5 | E7: 1.5
A8: A3 | B8: SENAI | C8: 1 | E8: 1
A9: A4 | B9: INCRA | C9: 0.2 | E9: 0.2
A10: A5 | B10: SEBRAE | C10: 0.6 | E10: 0.6
A11: A6 | B11: Salário Educação | C11: 2.5 | E11: 2.5
A12: A7 | B12: Seguro Contra Acidentes de Trabalho | C12: 3 | E12: 3
A13: A8 | B13: FGTS | C13: 8 | E13: 8
A14: A9 | B14: SECONCI | C14: 0 | E14: 0
B15: TOTAL | C15: 36.8 | E15: 36.8
A17: B | B17: GRUPO B
A18: B1 | B18: Repouso Semanal Remunerado | C18: 17.85 | E18: 0
A19: B2 | B19: Feriados | C19: 3.71 | E19: 0
A20: B3 | B20: Auxíl io - Enfermidade | C20: 0.87 | E20: 0.66
A21: B4 | B21: 13º Salário | C21: 11.03 | E21: 8.33
A22: B5 | B22: Licença Paternidade | C22: 0.07 | E22: 0.05
A23: B6 | B23: Faltas Justificadas | C23: 0.74 | E23: 0.56
A24: B7 | B24: Dias de Chuvas | C24: 1.59 | E24: 0
A25: B8 | B25: Auxíl io Acidente de Trabalho | C25: 0.11 | E25: 0.08
A26: B9 | B26: Férias Gozadas | C26: 12.35 | E26: 9.33
A27: B10 | B27: Salário Maternidade | C27: 0.04 | E27: 0.03
B28: TOTAL | C28: 48.36 | E28: 19.04
A30: C | B30: GRUPO C
A31: C1 | B31: Aviso Prévio Indenizado | C31: 5.52 | E31: 4.17
A32: C2 | B32: Aviso Prévio Trabalhado | C32: 0.13 | E32: 0.1
A33: C3 | B33: Férias Indenizadas | C33: 1.72 | E33: 1.3
A34: C4 | B34: Depósito Rescisão Sem Justa Causa | C34: 2.87 | E34: 2.17
A35: C5 | B35: Indenização Adicional | C35: 0.46 | E35: 0.35
B36: TOTAL | C36: 10.7 | E36: 8.09
A38: D | B38: GRUPO D
A39: D1 | B39: Reincidência de Grupo A sobre Grupo B | C39: 17.8 | E39: 7.01
A40: D2 | B40: Reincidência de Grupo A sobre Aviso Prévio Trabalhado e Reincidência do FGTS sobre Aviso Prévio Indenizado | C40: 0.49 | E40: 0.37
B41: TOTAL | C41: 18.29 | E41: 7.38
B43: A + B + C + D = | C43: 114.15 | E43: 71.31
A45: COD | B45: DESCRIÇÃO | C45: HORISTA % | E45: MENSALISTA %
A47: A | B47: GRUPO A
A48: A1 | B48: INSS | C48: 20 | E48: 20
A49: A2 | B49: SESI | C49: 1.5 | E49: 1.5
A50: A3 | B50: SENAI | C50: 1 | E50: 1
A51: A4 | B51: INCRA | C51: 0.2 | E51: 0.2
A52: A5 | B52: SEBRAE | C52: 0.6 | E52: 0.6
A53: A6 | B53: Salário Educação | C53: 2.5 | E53: 2.5
A54: A7 | B54: Seguro Contra Acidentes de Trabalho | C54: 3 | E54: 3
A55: A8 | B55: FGTS | C55: 8 | E55: 8
A56: A9 | B56: SECONCI | C56: 0 | E56: 0
B57: TOTAL | C57: 36.8 | E57: 36.8
A59: B | B59: GRUPO B
A60: B1 | B60: Repouso Semanal Remunerado | C60: 17.86 | E60: 0
A61: B2 | B61: Feriados | C61: 3.71 | E61: 0
A62: B3 | B62: Auxílio - Enfermidade | C62: 0.86 | E62: 0.65
A63: B4 | B63: 13º Salário | C63: 11.07 | E63: 8.33
A64: B5 | B64: Licença Paternidade | C64: 0.07 | E64: 0.05
A65: B6 | B65: Faltas Justificadas | C65: 0.74 | E65: 0.56
A66: B7 | B66: Dias de Chuvas | C66: 1.64 | E66: 0
A67: B8 | B67: Auxílio Acidente de Trabalho | C67: 0.1 | E67: 0.07
A68: B9 | B68: Férias Gozadas | C68: 12.98 | E68: 9.77
A69: B10 | B69: Salário Maternidade | C69: 0.03 | E69: 0.03
B70: TOTAL | C70: 49.06 | E70: 19.46
A72: C | B72: GRUPO C
A73: C1 | B73: Aviso Prévio Indenizado | C73: 5.54 | E73: 4.17
A74: C2 | B74: Aviso Prévio Trabalhado | C74: 0.13 | E74: 0.1
A75: C3 | B75: Férias Indenizadas | C75: 1.81 | E75: 1.36
A76: C4 | B76: Depósito Rescisão Sem Justa Causa | C76: 2.75 | E76: 2.07
A77: C5 | B77: Indenização Adicional | C77: 0.47 | E77: 0.35
B78: TOTAL | C78: 10.7 | E78: 8.05
A80: D | B80: GRUPO D
A81: D1 | B81: Reincidência de Grupo A sobre Grupo B | C81: 18.05 | E81: 7.16
A82: D2 | B82: Reincidência de Grupo A sobre Aviso Prévio Trabalhado e Reincidência do FGTS sobre Aviso Prévio Indenizado | C82: 0.49 | E82: 0.37
B83: TOTAL | C83: 18.54 | E83: 7.53
B85: A + B + C + D = | C85: 115.1 | E85: 71.84
